Metadata-Version: 2.1
Name: epam-ai-run-codemie-tools
Version: 0.0.306
Summary: Package with EPAM AI/Run CodeMie tools for AI Agents
Author: CodeMie Team
Author-email: codemie@epam.com
Requires-Python: >=3.12,<4.0
Classifier: Programming Language :: Python :: 3
Classifier: Programming Language :: Python :: 3.12
Requires-Dist: PyGithub (>=2.2.0,<3.0.0)
Requires-Dist: atlassian-python-api (>=3.41.14,<4.0.0)
Requires-Dist: azure-core (>=1.30.2,<2.0.0)
Requires-Dist: azure-identity (>=1.16.0,<2.0.0)
Requires-Dist: boto3 (>=1.34.147,<2.0.0)
Requires-Dist: chardet (>=5.2.0,<6.0.0)
Requires-Dist: codeboxapi (>=0.1.21,<0.2.0)
Requires-Dist: elastic-transport (==8.13.1)
Requires-Dist: elasticsearch (==8.14.0)
Requires-Dist: flake8 (>=7.1.1,<8.0.0)
Requires-Dist: gitpython (>=3.1.32,<4.0.0)
Requires-Dist: google-api-python-client (>=2.137.0,<3.0.0)
Requires-Dist: googlemaps (>=4.10.0,<5.0.0)
Requires-Dist: httpx (>=0.27.0,<0.28.0)
Requires-Dist: jupyter-kernel-gateway (>=3.0.1,<4.0.0)
Requires-Dist: kubernetes (>=30.1.0,<31.0.0)
Requires-Dist: langchain (==0.3.3)
Requires-Dist: langchain-community (>=0.3.2,<0.4.0)
Requires-Dist: langchain-core (>=0.3.11,<0.4.0)
Requires-Dist: langchain-experimental (>=0.3.2,<0.4.0)
Requires-Dist: langchain-google-community (==2.0.1)
Requires-Dist: langchain-openai (>=0.2.2,<0.3.0)
Requires-Dist: markdownify (>=0.13.1,<0.14.0)
Requires-Dist: matplotlib (>=3.9.1,<4.0.0)
Requires-Dist: openapi-schema-pydantic (>=1.2.4,<2.0.0)
Requires-Dist: pandas (>=2.2.2,<3.0.0)
Requires-Dist: psycopg (>=3.2.3,<4.0.0)
Requires-Dist: pydantic (>=2.9.2,<3.0.0)
Requires-Dist: pydantic-settings (>=2.5.2,<3.0.0)
Requires-Dist: pymysql (>=1.1.1,<2.0.0)
Requires-Dist: pytest (>=8.3.1,<9.0.0)
Requires-Dist: pytest-asyncio (>=0.23.7,<0.24.0)
Requires-Dist: pytest-cov (>=5.0.0,<6.0.0)
Requires-Dist: pytest-env (>=1.1.3,<2.0.0)
Requires-Dist: pytest-mock (>=3.14.0,<4.0.0)
Requires-Dist: python-dotenv (>=1.0.0,<2.0.0)
Requires-Dist: python-gitlab (>=4.6.0,<5.0.0)
Requires-Dist: ruff (>=0.5.4,<0.6.0)
Requires-Dist: sqlalchemy (>=2.0.35,<3.0.0)
Requires-Dist: tiktoken (>=0.7.0,<0.8.0)
Requires-Dist: wikipedia (>=1.4.0,<2.0.0)
